md2html/__init__.py
md2html/__main__.py
md2html/github-markdown.css
md2html/main.css
md2html/md2html.py
md2html/pygments.css
md2html/style-dark.css
md2html/style-sidebar-toc.css
md2html_phuker-0.5.2.dist-info/LICENSE
md2html_phuker-0.5.2.dist-info/METADATA
md2html_phuker-0.5.2.dist-info/WHEEL
md2html_phuker-0.5.2.dist-info/entry_points.txt
md2html_phuker-0.5.2.dist-info/top_level.txt
md2html_phuker-0.5.2.dist-info/RECORD
